sknet/__init__.py
sknet/network_construction/__init__.py
sknet/network_construction/dataset_constructors.py
sknet/network_construction/general_constructors.py
sknet/network_construction/time_series_constructors.py
sknet/network_construction/tests/__init__.py
sknet/network_construction/tests/test_network_construction.py
sknet/semi_supervised/__init__.py
sknet/semi_supervised/modularity_label_propagation.py
sknet/supervised/__init__.py
sknet/supervised/ease_of_access.py
sknet/supervised/high_level_classification.py
sknet/supervised/tests/__init__.py
sknet/supervised/tests/test_ease_of_access.py
sknet/supervised/tests/test_high_level_classification.py
sknet/unsupervised/__init__.py
sknet/unsupervised/stochastic_particle_competition.py
sknet/utils/__init__.py
sknet/utils/low_level_models_handler.py
sknet/utils/network_metrics_handler.py
sknet/utils/network_types_handler.py
scikit_net-0.0.4.dist-info/LICENSE
scikit_net-0.0.4.dist-info/METADATA
scikit_net-0.0.4.dist-info/WHEEL
scikit_net-0.0.4.dist-info/top_level.txt
scikit_net-0.0.4.dist-info/RECORD
