Metadata-Version: 2.1
Name: scikit-net
Version: 0.0.4
Summary: Machine Learning in Complex Networks
Home-page: https://github.com/TNanukem/scikit-net
Download-URL: https://github.com/TNanukem/scikit-net/archive/refs/tags/v0.0.1.tar.gz
Author: Tiago Toledo Jr
Author-email: tiago.nanu@gmail.com
License: MIT
Keywords: Machine Learning,Complex Networks
Classifier: License :: OSI Approved :: MIT License
Classifier: Programming Language :: Python :: 3
Classifier: Programming Language :: Python :: 3.8
License-File: LICENSE
Requires-Dist: attrs
Requires-Dist: decorator
Requires-Dist: importlib-metadata
Requires-Dist: iniconfiggiotto-tda
Requires-Dist: joblib
Requires-Dist: networkx
Requires-Dist: numpy
Requires-Dist: packaging
Requires-Dist: pandas
Requires-Dist: pluggy
Requires-Dist: py
Requires-Dist: pyparsing
Requires-Dist: pytest
Requires-Dist: python-dateutil
Requires-Dist: pytz
Requires-Dist: scikit-learn
Requires-Dist: scipy
Requires-Dist: six
Requires-Dist: sklearn
Requires-Dist: threadpoolctl
Requires-Dist: toml
Requires-Dist: tqdm
Requires-Dist: typing-extensions
Requires-Dist: zipp
